edterm/__init__.py
edterm/data_reader.py
edterm/edterm.py
edterm-0.1.5.dist-info/LICENSE
edterm-0.1.5.dist-info/METADATA
edterm-0.1.5.dist-info/WHEEL
edterm-0.1.5.dist-info/entry_points.txt
edterm-0.1.5.dist-info/top_level.txt
edterm-0.1.5.dist-info/RECORD
