Metadata-Version: 2.1
Name: edterm
Version: 0.1.5
Summary: A terminal-based GROMACS EDR data plotting tool
Home-page: https://github.com/mattiafelice-palermo/edterm
Author: Mattia Felice Palermo
Author-email: mattiafelice.palermo@gmail.com
Classifier: Development Status :: 3 - Alpha
Classifier: Intended Audience :: Science/Research
Classifier: Topic :: Scientific/Engineering :: Visualization
Classifier: License :: OSI Approved :: MIT License
Classifier: Programming Language :: Python :: 3
Classifier: Programming Language :: Python :: 3.7
Classifier: Programming Language :: Python :: 3.8
Classifier: Programming Language :: Python :: 3.9
Classifier: Programming Language :: Python :: 3.10
Requires-Python: >=3.7
License-File: LICENSE
Requires-Dist: pandas
Requires-Dist: plotext
Requires-Dist: panedr
